youtube_transcript_api/__init__.py
youtube_transcript_api/__main__.py
youtube_transcript_api/_api.py
youtube_transcript_api/_cli.py
youtube_transcript_api/_errors.py
youtube_transcript_api/_html_unescaping.py
youtube_transcript_api/_settings.py
youtube_transcript_api/_transcripts.py
youtube_transcript_api/formatters.py
youtube_transcript_api/test/__init__.py
youtube_transcript_api/test/test_api.py
youtube_transcript_api/test/test_cli.py
youtube_transcript_api/test/test_formatters.py
youtube_transcript_api/test/assets/__init__.py
youtube_transcript_api-0.6.1.dist-info/LICENSE
youtube_transcript_api-0.6.1.dist-info/METADATA
youtube_transcript_api-0.6.1.dist-info/WHEEL
youtube_transcript_api-0.6.1.dist-info/entry_points.txt
youtube_transcript_api-0.6.1.dist-info/top_level.txt
youtube_transcript_api-0.6.1.dist-info/RECORD
