Metadata-Version: 2.1
Name: youtube-transcript-api
Version: 0.6.1
Summary: This is an python API which allows you to get the transcripts/subtitles for a given YouTube video. It also works for automatically generated subtitles, supports translating subtitles and it does not require a headless browser, like other selenium based solutions do!
Home-page: https://github.com/jdepoix/youtube-transcript-api
Author: Jonas Depoix
Author-email: jonas.depoix@web.de
License: UNKNOWN
Keywords: youtube-api subtitles youtube transcripts transcript subtitle youtube-subtitles youtube-transcripts cli
Platform: UNKNOWN
Classifier: Programming Language :: Python :: 3.5
Classifier: Programming Language :: Python :: 3.6
Classifier: Programming Language :: Python :: 3.7
Classifier: Programming Language :: Python :: 3.8
Classifier: License :: OSI Approved :: MIT License
Classifier: Operating System :: OS Independent
